pcf8574_simulation/__init__.py
pcf8574_simulation/pcf8574_simulation.py
pcf8574_simulation-0.0.1.dist-info/METADATA
pcf8574_simulation-0.0.1.dist-info/WHEEL
pcf8574_simulation-0.0.1.dist-info/licenses/LICENSE
pcf8574_simulation-0.0.1.dist-info/RECORD
