Metadata-Version: 2.4
Name: pcf8574_simulation
Version: 0.0.1
Summary: A replacement of the PCF8574 class for testing purposes on devices without i2c bus hardware.
Project-URL: Repository, https://codeberg.org/Foerderverein_DresdnerParkeisenbahn_eV/pcf8574_simulation
Author-email: Timo Klinge <kl.timo@outlook.de>
License-Expression: MIT
License-File: LICENSE
Classifier: Operating System :: OS Independent
Classifier: Programming Language :: Python :: 3
Requires-Python: >=3.6
